pywapor/__init__.py
pywapor/et_look.py
pywapor/post_et_look.py
pywapor/pre_et_look.py
pywapor/pre_se_root.py
pywapor/se_root.py
pywapor/collect/__init__.py
pywapor/collect/accounts.py
pywapor/collect/downloader.py
pywapor/collect/product/CHIRPS.py
pywapor/collect/product/COPERNICUS.py
pywapor/collect/product/ERA5.py
pywapor/collect/product/GEOS5.py
pywapor/collect/product/GLO30.txt
pywapor/collect/product/GLO90.txt
pywapor/collect/product/GLOBCOVER.py
pywapor/collect/product/MERRA2.py
pywapor/collect/product/MODIS.py
pywapor/collect/product/MODIS_tiles.geojson
pywapor/collect/product/PROBAV.py
pywapor/collect/product/SENTINEL2.py
pywapor/collect/product/SENTINEL3.py
pywapor/collect/product/SRTM.py
pywapor/collect/product/SRTM30_tiles.geojson
pywapor/collect/product/STATICS.py
pywapor/collect/product/VIIRSL1.py
pywapor/collect/product/__init__.py
pywapor/collect/product/Landsat/C2L2SP.py
pywapor/collect/product/Landsat/__init__.py
pywapor/collect/protocol/__init__.py
pywapor/collect/protocol/cds.py
pywapor/collect/protocol/cog.py
pywapor/collect/protocol/crawler.py
pywapor/collect/protocol/opendap.py
pywapor/collect/protocol/projections.py
pywapor/collect/protocol/sentinelapi.py
pywapor/enhancers/__init__.py
pywapor/enhancers/apply_enhancers.py
pywapor/enhancers/dem.py
pywapor/enhancers/gap_fill.py
pywapor/enhancers/lulc.py
pywapor/enhancers/other.py
pywapor/enhancers/pressure.py
pywapor/enhancers/temperature.py
pywapor/enhancers/wind.py
pywapor/enhancers/dms/__init__.py
pywapor/enhancers/dms/pyDMS.py
pywapor/enhancers/dms/pyDMS_utils.py
pywapor/enhancers/dms/thermal_sharpener.py
pywapor/et_look_dev/__init__.py
pywapor/et_look_dev/biomass.py
pywapor/et_look_dev/clear_sky_radiation.py
pywapor/et_look_dev/constants.py
pywapor/et_look_dev/evapotranspiration.py
pywapor/et_look_dev/leaf.py
pywapor/et_look_dev/meteo.py
pywapor/et_look_dev/neutral.py
pywapor/et_look_dev/radiation.py
pywapor/et_look_dev/resistance.py
pywapor/et_look_dev/roughness.py
pywapor_test-3.1.7.dist-info/LICENSE
pywapor_test-3.1.7.dist-info/METADATA
pywapor_test-3.1.7.dist-info/WHEEL
pywapor_test-3.1.7.dist-info/top_level.txt
pywapor_test-3.1.7.dist-info/RECORD
