Metadata-Version: 2.1
Name: pywapor-test
Version: 3.1.7
Home-page: https://www.fao.org/aquastat/py-wapor/
Author: FAO
Author-email: bert.coerver@fao.org
License: Apache
Classifier: Operating System :: OS Independent
Classifier: Programming Language :: Python :: 3.7
Classifier: Programming Language :: Python :: 3.8
Classifier: Programming Language :: Python :: 3.9
Classifier: Programming Language :: Python :: 3.10
Requires-Python: >=3.7
License-File: LICENSE
Requires-Dist: gdal
Requires-Dist: xarray (>=0.20)
Requires-Dist: numpy
Requires-Dist: pydap
Requires-Dist: pandas
Requires-Dist: requests
Requires-Dist: matplotlib
Requires-Dist: netcdf4 (<1.6.0)
Requires-Dist: pyproj
Requires-Dist: scipy
Requires-Dist: pycurl
Requires-Dist: pyshp
Requires-Dist: joblib
Requires-Dist: bs4
Requires-Dist: rasterio
Requires-Dist: bottleneck (>=1.3.1)
Requires-Dist: geojson
Requires-Dist: tqdm
Requires-Dist: dask
Requires-Dist: rioxarray
Requires-Dist: python-log-indenter
Requires-Dist: cryptography
Requires-Dist: pyvis
Requires-Dist: cachetools
Requires-Dist: cdsapi
Requires-Dist: sentinelsat
Requires-Dist: shapely
Requires-Dist: lxml
Requires-Dist: geopy
Requires-Dist: sklearn
Requires-Dist: numba
Requires-Dist: importlib-metadata (==4.13.0)
